tyger/__init__.py
tyger/driver.py
tyger/main.py
tyger/parser.py
tyger/phase.py
tyger/discipline/ToAST.py
tyger/discipline/__init__.py
tyger/discipline/evidence.py
tyger/discipline/types.py
tyger/discipline/base/__init__.py
tyger/discipline/base/evidence.py
tyger/discipline/base/types.py
tyger/discipline/sectypes/ToAST.py
tyger/discipline/sectypes/__init__.py
tyger/discipline/sectypes/evidence.py
tyger/discipline/sectypes/types.py
tyger/discipline/simple/ToAST.py
tyger/discipline/simple/__init__.py
tyger/discipline/simple/evidence.py
tyger/discipline/simple/types.py
tyger/phases/__init__.py
tyger/phases/dependency_collection.py
tyger/phases/elaboration.py
tyger/phases/type_check.py
tyger/runtime/__init__.py
tyger/runtime/contextual_information.py
tyger/runtime/custom_builtins.py
tyger/runtime/import_handler.py
tyger/runtime/scopes.py
tyger/runtime/wrapper.py
tyger-1.0.dist-info/METADATA
tyger-1.0.dist-info/WHEEL
tyger-1.0.dist-info/entry_points.txt
tyger-1.0.dist-info/licenses/LICENSE
tyger-1.0.dist-info/RECORD
