Metadata-Version: 2.4
Name: tyger
Version: 1.0
Summary: Tyger is a simple type analysis tool that provides the foundations to implement different typing disciplines in Python.
Project-URL: Homepage, https://github.com/pleiad/GPython
Project-URL: Team, https://pleiad.cl
Author: PLEIAD
License-File: LICENSE
Classifier: License :: OSI Approved :: MIT License
Classifier: Operating System :: OS Independent
Classifier: Programming Language :: Python :: 3
Requires-Python: >=3.11
